LICENSE
diffalarm/__init__.py
diffalarm/__main__.py
diffalarm/beep.py
diffalarm-0.1.1.dist-info/entry_points.txt
diffalarm-0.1.1.dist-info/LICENSE
diffalarm-0.1.1.dist-info/WHEEL
diffalarm-0.1.1.dist-info/METADATA
diffalarm-0.1.1.dist-info/RECORD
