Metadata-Version: 2.1
Name: diffalarm
Version: 0.1.1
Summary: alarms when web page has diff
Home-page: https://github.com/scarf005/diffalarm
License: MIT
Author: scarf
Author-email: greenscarf005@gmail.com
Requires-Python: >=3.10,<4.0
Classifier: License :: OSI Approved :: MIT License
Classifier: Programming Language :: Python :: 3
Classifier: Programming Language :: Python :: 3.10
Requires-Dist: beepy (>=1.0.7,<2.0.0)
Requires-Dist: bs4 (>=0.0.1,<0.0.2)
Requires-Dist: docopt (>=0.6.2,<0.7.0)
Requires-Dist: requests (>=2.28.1,<3.0.0)
Project-URL: Repository, https://github.com/scarf005/diffalarm
